codeskeleton
