Metadata-Version: 1.1
Name: codeskeleton
Version: 1.0.1
Summary: General purpose code skeleton solution.
Home-page: UNKNOWN
Author: Appresso AS
Author-email: post@appresso.no
License: BSD
Platform: UNKNOWN
Classifier: Development Status :: 3 - Alpha
Classifier: Intended Audience :: Developers
Classifier: Topic :: Software Development :: Code Generators
Classifier: License :: OSI Approved
Classifier: Programming Language :: Python :: 3
